{"testandroid": {
  "Rock28": {
    "id": 28,
    "text": "",
    "xCoord": 1000,
    "xSize": 200,
    "class": "Rock",
    "yCoord": 400,
    "type": 0,
    "ySize": 200
  },
  "Lumber20": {
    "id": 20,
    "text": "",
    "xCoord": 550,
    "xSize": 50,
    "class": "Lumber",
    "yCoord": 750,
    "type": 0,
    "ySize": 50
  },
  "Lumber21": {
    "id": 21,
    "text": "",
    "xCoord": 550,
    "xSize": 50,
    "class": "Lumber",
    "yCoord": 750,
    "type": 0,
    "ySize": 50
  },
  "StoneSign29": {
    "id": 29,
    "text": "",
    "xCoord": 600,
    "xSize": 400,
    "class": "StoneSign",
    "yCoord": 200,
    "type": 0,
    "ySize": 200
  },
  "Lumber22": {
    "id": 22,
    "text": "",
    "xCoord": 600,
    "xSize": 300,
    "class": "Lumber",
    "yCoord": 750,
    "type": 0,
    "ySize": 50
  },
  "Block4": {
    "id": 4,
    "text": "",
    "xCoord": 200,
    "xSize": 200,
    "class": "Block",
    "yCoord": 600,
    "type": 0,
    "ySize": 200
  },
  "Snake24": {
    "id": 24,
    "text": "",
    "xCoord": 650,
    "xSize": 164,
    "class": "Snake",
    "yCoord": 950,
    "type": 0,
    "ySize": 70
  },
  "Snake23": {
    "id": 23,
    "text": "",
    "xCoord": 400,
    "xSize": 164,
    "class": "Snake",
    "yCoord": 850,
    "type": 0,
    "ySize": 70
  },
  "Box0": {
    "id": 0,
    "text": "",
    "xCoord": 0,
    "xSize": 200,
    "class": "Box",
    "yCoord": 800,
    "type": 0,
    "ySize": 200
  },
  "Lumber10": {
    "id": 10,
    "text": "",
    "xCoord": 550,
    "xSize": 50,
    "class": "Lumber",
    "yCoord": 750,
    "type": 0,
    "ySize": 50
  },
  "Lumber11": {
    "id": 11,
    "text": "",
    "xCoord": 550,
    "xSize": 50,
    "class": "Lumber",
    "yCoord": 750,
    "type": 0,
    "ySize": 50
  },
  "Grass31": {
    "id": 31,
    "text": "",
    "xCoord": 1200,
    "xSize": 200,
    "class": "Grass",
    "yCoord": 800,
    "type": 0,
    "ySize": 200
  },
  "Glass3": {
    "id": 3,
    "text": "",
    "xCoord": 200,
    "xSize": 50,
    "class": "Glass",
    "yCoord": 200,
    "type": 0,
    "ySize": 250
  },
  "Lumber14": {
    "id": 14,
    "text": "",
    "xCoord": 550,
    "xSize": 50,
    "class": "Lumber",
    "yCoord": 750,
    "type": 0,
    "ySize": 50
  },
  "courseProperties": {
    "maxSpeedLevel": 5,
    "name": "testandroid",
    "minSpeedLevel": 0,
    "courseSize": 2200,
    "randomAmount": 4,
    "difficultyLevel": 0
  },
  "Lumber15": {
    "id": 15,
    "text": "",
    "xCoord": 550,
    "xSize": 50,
    "class": "Lumber",
    "yCoord": 750,
    "type": 0,
    "ySize": 50
  },
  "Lumber12": {
    "id": 12,
    "text": "",
    "xCoord": 550,
    "xSize": 50,
    "class": "Lumber",
    "yCoord": 750,
    "type": 0,
    "ySize": 50
  },
  "Glass30": {
    "id": 30,
    "text": "",
    "xCoord": 500,
    "xSize": 300,
    "class": "Glass",
    "yCoord": 400,
    "type": 0,
    "ySize": 50
  },
  "Lumber13": {
    "id": 13,
    "text": "",
    "xCoord": 550,
    "xSize": 50,
    "class": "Lumber",
    "yCoord": 750,
    "type": 0,
    "ySize": 50
  },
  "Tire1": {
    "id": 1,
    "text": "",
    "xCoord": 0,
    "xSize": 200,
    "class": "Tire",
    "yCoord": 600,
    "type": 0,
    "ySize": 200
  },
  "Lumber19": {
    "id": 19,
    "text": "",
    "xCoord": 550,
    "xSize": 50,
    "class": "Lumber",
    "yCoord": 750,
    "type": 0,
    "ySize": 50
  },
  "Lumber18": {
    "id": 18,
    "text": "",
    "xCoord": 550,
    "xSize": 50,
    "class": "Lumber",
    "yCoord": 750,
    "type": 0,
    "ySize": 50
  },
  "Sign26": {
    "id": 26,
    "text": "ghfg",
    "xCoord": 1000,
    "xSize": 200,
    "class": "Sign",
    "yCoord": 800,
    "type": 0,
    "ySize": 200
  },
  "Lumber17": {
    "id": 17,
    "text": "",
    "xCoord": 550,
    "xSize": 50,
    "class": "Lumber",
    "yCoord": 750,
    "type": 0,
    "ySize": 50
  },
  "Water25": {
    "id": 25,
    "text": "",
    "xCoord": 800,
    "xSize": 200,
    "class": "Water",
    "yCoord": 900,
    "type": 0,
    "ySize": 200
  },
  "Lumber16": {
    "id": 16,
    "text": "",
    "xCoord": 550,
    "xSize": 50,
    "class": "Lumber",
    "yCoord": 750,
    "type": 0,
    "ySize": 50
  },
  "Lumber8": {
    "id": 8,
    "text": "",
    "xCoord": 400,
    "xSize": 50,
    "class": "Lumber",
    "yCoord": 350,
    "type": 0,
    "ySize": 400
  },
  "Lumber9": {
    "id": 9,
    "text": "",
    "xCoord": 550,
    "xSize": 50,
    "class": "Lumber",
    "yCoord": 750,
    "type": 0,
    "ySize": 50
  },
  "IronBox2": {
    "id": 2,
    "text": "",
    "xCoord": 0,
    "xSize": 200,
    "class": "IronBox",
    "yCoord": 400,
    "type": 0,
    "ySize": 200
  },
  "Bush6": {
    "id": 6,
    "text": "",
    "xCoord": 200,
    "xSize": 100,
    "class": "Bush",
    "yCoord": 900,
    "type": 0,
    "ySize": 100
  },
  "Bush7": {
    "id": 7,
    "text": "",
    "xCoord": 300,
    "xSize": 100,
    "class": "Bush",
    "yCoord": 900,
    "type": 0,
    "ySize": 100
  },
  "Bush5": {
    "id": 5,
    "text": "",
    "xCoord": 200,
    "xSize": 100,
    "class": "Bush",
    "yCoord": 800,
    "type": 0,
    "ySize": 100
  },
  "Barrel27": {
    "id": 27,
    "text": "",
    "xCoord": 1000,
    "xSize": 200,
    "class": "Barrel",
    "yCoord": 600,
    "type": 0,
    "ySize": 200
  }
}}